{
    "camera": {
        "look_at": [
            0,
            0,
            0
        ],
        "look_from": [
            8.0,
            4.0,
            10.0
        ]
    },
    "objects": [
        {
            "Sphere": {
                "center": [
                    0,
                    -1000,
                    0
                ],
                "radius": 1000,
                "material": {
                    "Lambertian": {
                        "albedo": [
                            0.5,
                            0.5,
                            0.5
                        ]
                    }
                }
            }
        },
        {
            "Sphere": {
                "center": [
                    4.0,
                    0.992,
                    -4.0
                ],
                "radius": 1,
                "material": {
                    "Metal": {
                        "albedo": [
                            0.7699705292313669,
                            0.7663058985735614,
                            0.3754759410374021
                        ],
                        "fuzz": 0.32105470784354206
                    }
                }
            }
        },
        {
            "Sphere": {
                "center": [
                    0.0,
                    1.0,
                    -4.0
                ],
                "radius": 1,
                "material": {
                    "Metal": {
                        "albedo": [
                            0.27742492045556144,
                            0.06902384519744287,
                            0.45135539518389023
                        ],
                        "fuzz": 0.998540804889273
                    }
                }
            }
        },
        {
            "Sphere": {
                "center": [
                    -4.0,
                    0.992,
                    -4.0
                ],
                "radius": 1,
                "material": {
                    "Lambertian": {
                        "albedo": [
                            0.5843435078536374,
                            0.3529724468763361,
                            0.4880805751349081
                        ]
                    }
                }
            }
        },
        {
            "Sphere": {
                "center": [
                    4.0,
                    0.992,
                    0.0
                ],
                "radius": 1,
                "material": {
                    "Dielectric": {
                        "refraction_index": 1.5
                    }
                }
            }
        },
        {
            "Sphere": {
                "center": [
                    0.0,
                    1.0,
                    0.0
                ],
                "radius": 1,
                "material": {
                    "Metal": {
                        "albedo": [
                            0.5657382011284674,
                            0.9115284321190846,
                            0.4349087054903584
                        ],
                        "fuzz": 0.3284132432785838
                    }
                }
            }
        },
        {
            "Sphere": {
                "center": [
                    -4.0,
                    0.992,
                    0.0
                ],
                "radius": 1,
                "material": {
                    "Metal": {
                        "albedo": [
                            0.7560196610601411,
                            0.15792013901512003,
                            0.7645934530359411
                        ],
                        "fuzz": 0.05704878707260219
                    }
                }
            }
        },
        {
            "Sphere": {
                "center": [
                    4.0,
                    0.992,
                    4.0
                ],
                "radius": 1,
                "material": {
                    "Lambertian": {
                        "albedo": [
                            0.9028456570354452,
                            0.4235898197098297,
                            0.2985540341230657
                        ]
                    }
                }
            }
        },
        {
            "Sphere": {
                "center": [
                    0.0,
                    1.0,
                    4.0
                ],
                "radius": 1,
                "material": {
                    "Metal": {
                        "albedo": [
                            0.3097032602084183,
                            0.5450938225408686,
                            0.33631996313663426
                        ],
                        "fuzz": 0.30570545565093354
                    }
                }
            }
        },
        {
            "Sphere": {
                "center": [
                    -4.0,
                    0.992,
                    4.0
                ],
                "radius": 1,
                "material": {
                    "Lambertian": {
                        "albedo": [
                            0.3203312040165489,
                            0.6186850755987924,
                            0.0018598509778454675
                        ]
                    }
                }
            }
        }
    ]
}